adbshellexecuter/LICENSE.txt
adbshellexecuter/README.MD
adbshellexecuter/__init__.py
adbshellexecuter/requirements.txt
adbshellexecuter/thirdparty.json
adbshellexecuter-0.12.dist-info/LICENSE.rst
adbshellexecuter-0.12.dist-info/METADATA
adbshellexecuter-0.12.dist-info/WHEEL
adbshellexecuter-0.12.dist-info/top_level.txt
adbshellexecuter-0.12.dist-info/RECORD
