Metadata-Version: 2.1
Name: adbshellexecuter
Version: 0.12
Summary: A class to execute ADB (Android Debug Bridge) commands on multiple operating systems.
Home-page: https://github.com/hansalemaos/adbshellexecuter
Author: Johannes Fischer
Author-email: aulasparticularesdealemaosp@gmail.com
License: MIT
Keywords: android,adb
Classifier: Development Status :: 4 - Beta
Classifier: Programming Language :: Python :: 3 :: Only
Classifier: Programming Language :: Python :: 3.10
Classifier: Topic :: Software Development :: Libraries :: Python Modules
Classifier: Topic :: Utilities
License-File: LICENSE.rst
Requires-Dist: exceptdrucker
Requires-Dist: osversionchecker
